Metadata-Version: 2.1
Name: tapo-plug
Version: 0.1
Summary: A REST API warper for TP-Link Tapo P100/P105.
Home-page: https://gitlab.com/Naqwada/TapoPlug-Rest-API
Author: Samy Younsi (Naqwada)
Author-email: naqwada@pm.me
License: MIT
Keywords: TP_LINK,tapo,smart plug,iot,p100,p105
Platform: UNKNOWN
Classifier: Programming Language :: Python :: 3
Classifier: License :: OSI Approved :: MIT License
